{
  "id": 13447,
  "name": "Trail Noturno de Valongo 2021",
  "location": "Valongo, Porto",
  "coordinates": {
    "lat": 41.1934558,
    "lon": -8.5012261
  },
  "country": "Portugal",
  "locality": "Porto",
  "distances": [],
  "types": [
    "trail"
  ],
  "images": [
    "media/ea5024e53f028186beeff9fa75baa649"
  ],
  "start_date": "2021-12-11",
  "end_date": "2021-12-12",
  "circuit": [],
  "description": "\n<p>Prepara a Lanterna/Frontal para o Trail Noturno de Valongo 2021 <img decoding=\"async\" height=\"16\" width=\"16\" alt=\"💡\" src=\"https://static.xx.fbcdn.net/images/emoji.php/v9/t3c/1/16/1f4a1.png\"><img decoding=\"async\" height=\"16\" width=\"16\" alt=\"💡\" src=\"https://static.xx.fbcdn.net/images/emoji.php/v9/t3c/1/16/1f4a1.png\"> o resto tratamos nós..Dorsal, Chip, Medalha, T-shirt e o Jantar está incluído!!</p>\n",
  "description_short": "Trail nocturno desafiante por Valongo com todos os extras incluídos",
  "page": "https://stopandgo.com.pt/events/8o-tnv-trail-noturno-de-valongo?fbclid=IwAR2McBXU6YGEoTJtxB9V_5FHOIvxQPN77qOyV4RXQeTI8mOr2uy8WSjyJY0",
  "slug": "trail-noturno-de-valongo-2021",
  "administrative_area_level_1": "Porto",
  "administrative_area_level_2": "Valongo",
  "administrative_area_level_3": "Valongo",
  "district_code": 13
}
