{
  "id": 1384,
  "name": "8º Cross Noturno Da Batalha 2020",
  "location": "Batalha, Leiria",
  "coordinates": {
    "lat": 39.6583864,
    "lon": -8.8241787
  },
  "country": "Portugal",
  "locality": "Leiria",
  "distances": [
    7000,
    15000
  ],
  "types": [
    "trail",
    "cross-country",
    "walk"
  ],
  "images": [
    "media/6088cf7b1d7fe158c6d1f01924f57e0f"
  ],
  "start_date": "2020-05-09",
  "end_date": "2020-05-10",
  "circuit": [],
  "description": "<p>É uma organização do Atlético Clube da Batalha &#8211; ACB com apoio Câmara Municipal da Batalha e Junta Freguesia da Batalha. Trata-se de um evento de corrida e caminhada noturna em ambiente natural e histórico da Vila da Batalha.<br />\nÉ constituída no seu percurso por carreiros e caminhos desnivelados, para tal se aconselha alguma prudência aos participantes. Decorrerá durante a noite de 9 maio de 2020, com início previsto pelas 20horas.<br />\nHá dois níveis de dificuldade: o cross tem 15 quilómetros e a caminhada 7 km.</p>\n",
  "description_short": "Corrida noturna por caminhos desnivelados na histórica Vila da Batalha",
  "page": "https://www.facebook.com/events/1078591462481720/",
  "slug": "8o-cross-noturno-da-batalha-2020",
  "administrative_area_level_1": "Leiria",
  "administrative_area_level_2": "Batalha",
  "administrative_area_level_3": "Batalha",
  "district_code": 10
}
