{
  "id": 14837,
  "name": "Corrida/Caminhada Dia Da Mãe 1",
  "location": "Paredes, Porto",
  "coordinates": {
    "lat": 41.2051674,
    "lon": -8.3303867
  },
  "country": "Portugal",
  "locality": "Porto",
  "distances": [
    10000
  ],
  "types": [
    "run",
    "10k",
    "walk"
  ],
  "images": [
    "media/35054a31a5b0f1e12d2818c56b98ece5"
  ],
  "start_date": "2022-05-01",
  "end_date": "2022-05-02",
  "circuit": [],
  "description": "\n<p>Corrida/Caminhada Dia Da Mãe 1</p>\n",
  "description_short": "Evento desportivo dedicado às mães com percurso de cariz recreativo e familiar",
  "page": "https://www.queroir.pt/13gp-atletismo-de-rebordosa---corridacaminhada-dia-da-mae-1",
  "slug": "corrida-caminhada-dia-da-mae-1",
  "administrative_area_level_1": "Porto",
  "administrative_area_level_2": "Paredes",
  "administrative_area_level_3": "Paredes",
  "district_code": 13
}
