{
  "id": 14933,
  "name": "Corrida Noturna Praia da Caparica 2022",
  "location": "Costa da Caparica, Almada",
  "coordinates": {
    "lat": 38.64455299999999,
    "lon": -9.2333757
  },
  "country": "Portugal",
  "locality": "Setúbal",
  "distances": [
    1000,
    5000,
    10000
  ],
  "types": [
    "run",
    "10k",
    "kids"
  ],
  "images": [
    "media/4d5a9129d73e78e6a5ae1be4199e4081"
  ],
  "start_date": "2022-07-02",
  "end_date": "2022-07-03",
  "circuit": [],
  "description": "\n<p>Não fique em casa e corra pelas praias da Caparica! No próximo dia 02 de julho 2022, a<strong> 6</strong>ª<strong> Corrida Noturna Praia da Caparica 2022</strong>, lança o desafio de correr 10km ou correr/caminhar 5km. O primeiro km é feito em alcatrão e depois vem a areia! Contamos consigo?</p>\n\n\n\n<p>As crianças também terão uma prova de 1km!</p>\n",
  "description_short": "Corrida noturna desafiante pelas praias da Caparica com troço em alcatrão e areia",
  "page": "https://xistarca.pt/eventos/6a-corrida-noturna-costa-da-caparica-2022",
  "slug": "corrida-noturna-praia-da-caparica-2022",
  "administrative_area_level_1": "Setúbal",
  "administrative_area_level_2": "Almada",
  "administrative_area_level_3": "Costa da Caparica",
  "district_code": 15
}
