{
  "id": 15111,
  "name": "Corrida &#038; Marcha Passeio São João da Degola 2022",
  "location": "Manta Rota, Faro",
  "coordinates": {
    "lat": 37.16801710000001,
    "lon": -7.520460299999999
  },
  "country": "Portugal",
  "locality": "Faro",
  "distances": [
    10000
  ],
  "types": [
    "run",
    "10k",
    "walk"
  ],
  "images": [
    "media/e9ac2d0dfafeff23f5eceefb0143b28a"
  ],
  "start_date": "2022-08-28",
  "end_date": "2022-08-29",
  "circuit": [],
  "description": "\n<p>Corrida São João da Degola 2022</p>\n",
  "description_short": "Trail tradicional de São João nas colinas do norte de Portugal",
  "page": "https://acorrer.pt/eventos/info/2981",
  "slug": "corrida-sao-joao-da-degola-2022",
  "administrative_area_level_1": "Faro",
  "administrative_area_level_2": "Vila Real de Santo António",
  "administrative_area_level_3": "Vila Nova de Cacela",
  "district_code": 8
}
