{
  "id": 21130,
  "name": "Trail Póvoa de Varzim 2023",
  "location": "Póvoa de Varzim, Porto",
  "coordinates": {
    "lat": 41.3828815,
    "lon": -8.759989299999999
  },
  "country": "Portugal",
  "locality": "Porto",
  "distances": [
    6000,
    16000,
    25000
  ],
  "types": [
    "trail",
    "run",
    "walk"
  ],
  "images": [
    "media/a428b7eb642638b2cb9cde22f278ad76"
  ],
  "start_date": "2023-01-22",
  "end_date": "2023-01-23",
  "circuit": [],
  "description": "\n<p>O TPV &#8211; TRAIL PÓVOA DE VARZIM HELOISE CRUZ IMOBILIÁRIA é um evento organizado pelo Centro Desportivo e Cultural de Navais e conta com o apoio da Junta da União das Freguesias de Aguçadoura e Navais e da Câmara Municipal da Póvoa de Varzim. Este evento decorrerá no dia 22 de janeiro durante o dia, e inclui as seguintes provas:<br>• 16Km–Trail curto<br>• 25Km–Trail longo<br>• 6km &#8211; Caminhada<br>O evento percorrerá ambiente natural, rural e urbano do norte do concelho da Póvoa de Varzim, com início no Parque Desportivo Alberto Silva, em Navais – Póvoa de Varzim.</p>\n",
  "description_short": "Trail pela paisagem diversificada do norte da Póvoa de Varzim, entre zonas naturais, rurais e urbanas",
  "page": "https://stopandgo.net/event/?id=936",
  "slug": "trail-povoa-de-varzim-2023",
  "administrative_area_level_1": "Porto",
  "administrative_area_level_2": "Póvoa de Varzim",
  "administrative_area_level_3": "Póvoa de Varzim",
  "district_code": 13
}
