{
  "id": 2118,
  "name": "Family Challenge 2020",
  "location": "Jamor Jamor, Lisboa",
  "coordinates": {
    "lat": 38.7086142,
    "lon": -9.2608892
  },
  "country": "Portugal",
  "locality": "Lisboa",
  "distances": [
    800,
    3500,
    5000,
    10000
  ],
  "types": [
    "run",
    "10k",
    "kids"
  ],
  "images": [
    "media/747e3d7b2d91bb40ebf87d5d3f77a58f"
  ],
  "start_date": "2020-03-15",
  "end_date": "2020-03-16",
  "circuit": [],
  "description": "<p><b>O #FamilyChallenge2020</b> é uma corrida idealizada para toda a família, num circuito fechado com o perímetro de 3,5 km, com <strong>partida e chegada no Parque Urbano do Jamor</strong>. A Kids Race, para menores de 14 anos, terá um percurso de 800m.</p>\n<p><strong>Cada Família deverá inscrever-se com um nome de equipa</strong>. A Classificação será obtida através da soma dos pontos dos vários elementos da Família, nas diversas provas.</p>\n<p>Existirão classificações gerais de Equipas/Famílias e classificações individuais.</p>\n<p>&nbsp;</p>\n",
  "description_short": "Corrida familiar no Jamor com provas para todos os escalões etários",
  "page": "http://xistarca.pt/eventos/familychallenge2020",
  "slug": "family-challenge-2020",
  "administrative_area_level_1": "Lisboa",
  "administrative_area_level_2": "Oeiras",
  "administrative_area_level_3": "União das freguesias de Algés, Linda-a-Velha e Cruz Quebrada-Dafundo",
  "district_code": 11
}
