{
  "id": 2165,
  "name": "One Hour Challenge Lisboa 2020",
  "location": "Campo Grande, Lisboa",
  "coordinates": {
    "lat": 38.7511573,
    "lon": -9.1539178
  },
  "country": "Portugal",
  "locality": "Lisboa",
  "distances": [
    1500,
    5000,
    10000
  ],
  "types": [
    "10k",
    "run"
  ],
  "images": [
    "media/cbbe191a6daaf43be5d85351c0ed8fd7"
  ],
  "start_date": "2020-06-21",
  "end_date": "2020-06-22",
  "circuit": [],
  "description": "<p>A mais recente inovação no mundo da corrida chega a Portugal! <strong>O desafio? Correr o mais que puderes numa hora de prova, num circuito fechado de 1,5km.<br />\n</strong>Nesta prova, não competes para correr no menor tempo possível… competes para correr a maior distância possível! És só tu contra o relógio. Quão longe és capaz de ir?</p>\n",
  "description_short": "Desafio inovador de corrida em circuito fechado com meta de maior distância em uma hora",
  "page": "http://xistarca.pt/eventos/xistarcaonehourchallenge",
  "slug": "one-hour-challenge-lisboa-2020",
  "administrative_area_level_1": "Lisboa",
  "administrative_area_level_2": "Lisboa",
  "administrative_area_level_3": "Campo Grande",
  "district_code": 11
}
