{
  "id": 22030,
  "name": "Estrela Grande Trail 2023",
  "location": "Manteigas, Guarda",
  "coordinates": {
    "lat": 40.4022206,
    "lon": -7.538339300000001
  },
  "country": "Portugal",
  "locality": "Distrito da Guarda",
  "distances": [
    800,
    1300,
    2500,
    5000,
    8000,
    15000,
    26000,
    49000,
    85000
  ],
  "types": [
    "kids",
    "trail"
  ],
  "images": [
    "media/387123a9de263e9af4a0e13b2bf8e3a7"
  ],
  "start_date": "2023-05-13",
  "end_date": "2023-05-14",
  "circuit": [
    "ATRP"
  ],
  "description": "\n<p>O evento Estrela Grande Trail vai ocorrer entre 12 e 14 de Maio 2023 em Manteigas na Serra da Estrela.<br><br>PROVAS<br>• Estrela Grande Trail®: prova de corrida em montanha de 85 km com 5000 metros de desnível positivo;<br>• Estrela Orion Belt: prova de corrida em montanha de 49 km com 2500 metros de desnível positivo;<br>• Estrela Taurus: prova de corrida em montanha de 26 km com 1300 metros de desnível positivo;<br>• Estrela Ursa Minor: prova de corrida em montanha com 15K e 800 metros ddesnível positivo;<br>• Caminhada Estrela Geopark (8km);<br>• Estrela Trail Kids e Estrela Solidário</p>\n",
  "description_short": "Trail exigente pela Serra da Estrela com diferentes percursos de montanha em Manteigas, desde ultra trail a prova para crianças",
  "page": "https://stopandgo.net/events/estrela-grande-trail-2023",
  "slug": "estrela-grande-trail-2023",
  "administrative_area_level_1": "Distrito da Guarda",
  "administrative_area_level_2": "Manteigas",
  "administrative_area_level_3": null,
  "district_code": 9
}
