{
  "id": 29009,
  "name": "Povoação Trail 2024",
  "location": "Povoação, Açores",
  "coordinates": {
    "lat": 37.7486524,
    "lon": -25.2390903
  },
  "country": "Portugal",
  "locality": "Açores",
  "distances": [
    13000,
    25000,
    50000
  ],
  "types": [
    "run",
    "trail",
    "walk"
  ],
  "images": [
    "media/1f58fe6a07781290546d5d5d7e9faf89"
  ],
  "start_date": "2024-03-10",
  "end_date": "2024-03-11",
  "circuit": [
    "ATRP"
  ],
  "description": "\n<p>O “Povoação Trail” é um evento de Trail Running que percorre trilhos e caminhos no concelho da Povoação, enquadrado nas vertentes de Trail Ultra (50 kms), Trail Longo (25kms), Trail Sprint / Caminhada (13 kms).</p>\n\n\n\n<p></p>\n",
  "description_short": "Trail desafiante pelos trilhos tradicionais da Povoação, nos Açores, com diferentes percursos para todos os níveis",
  "page": "https://lap2go.com/pt/event/povoacao-trail-2024",
  "slug": "povoacao-trail-2024",
  "administrative_area_level_1": "Açores",
  "administrative_area_level_2": "Povoação",
  "administrative_area_level_3": "Povoação",
  "district_code": 20
}
