{
  "id": 30598,
  "name": "Corrida São João Braga 2024",
  "location": "Braga",
  "coordinates": {
    "lat": 41.5454486,
    "lon": -8.426506999999999
  },
  "country": "Portugal",
  "locality": "Braga",
  "distances": [
    5000,
    10000,
    12000
  ],
  "types": [
    "run",
    "10k",
    "walk"
  ],
  "images": [
    "media/0cb106f308b580d3ca5adee0745f5bf1"
  ],
  "start_date": "2024-06-30",
  "end_date": "2024-07-01",
  "circuit": [],
  "description": "\n<p>No mês mais popular do ano, não poderia faltar a Q8 corrida de São João de Braga, dia 30 de junho de 2024, às 9h30, a Cidade de Braga espera encher as ruas de alegria e diversão com este grande evento.</p>\n\n\n\n<p>Para além da corrida de 12 km haverá também uma caminhada com a distância de 5km, sem fins competitivos, ambos os percursos têm partida e chegada na Av. Paulo II.</p>\n\n\n\n<p>Por isso aperte os cordões e traga a boa disposição para a Q8 corrida de São João de Braga.</p>\n",
  "description_short": "Corrida festiva de São João a celebrar o espírito da cidade de Braga com partida e chegada na Avenida Paulo II",
  "page": "https://www.runporto.com/pt/eventos/corrida-de-sao-joao-de-braga/",
  "slug": "corrida-sao-joao-de-braga-2024",
  "administrative_area_level_1": "Braga",
  "administrative_area_level_2": "Braga",
  "administrative_area_level_3": null,
  "district_code": 3
}
