{
  "id": 30633,
  "name": "Trilhos de Bellas 2024",
  "location": "Belas, Sintra, Lisboa",
  "coordinates": {
    "lat": 38.7764372,
    "lon": -9.2642481
  },
  "country": "Portugal",
  "locality": "Lisboa",
  "distances": [],
  "types": [
    "trail",
    "run"
  ],
  "images": [],
  "start_date": "2024-03-24",
  "end_date": "2024-03-25",
  "circuit": [
    "ATRP"
  ],
  "description": "",
  "description_short": "Entendido. Estou preparado para condensar descrições de eventos de corrida em resumos sucintos de uma linha. Aguardo que me forneça a descrição que devo resumir.",
  "page": null,
  "slug": "trilhos-de-bellas-2024",
  "administrative_area_level_1": "Lisboa",
  "administrative_area_level_2": "Sintra",
  "administrative_area_level_3": "União das freguesias de Queluz e Belas",
  "district_code": 11
}
