{
  "id": 33788,
  "name": "Trail do Bom Despacho 2024",
  "location": "São Pedro de Peneferrin, Sintra",
  "coordinates": {
    "lat": 38.7911955,
    "lon": -9.3803024
  },
  "country": "Portugal",
  "locality": "Lisboa",
  "distances": [
    12000,
    25000
  ],
  "types": [
    "run",
    "trail",
    "walk"
  ],
  "images": [
    "media/9ea20135c274cabd59316740c03093d7"
  ],
  "start_date": "2024-05-19",
  "end_date": "2024-05-19",
  "circuit": [],
  "description": "\n<p>A associação Cultural e Recreativa ATEPS, irá organizar, a 19 de maio de 2024,  o Trail do Bom despacho 2024 em São Pedro de Peneferrin, concelho de Sintra. O Trail do Bom Despacho 2024 é uma prova de TrailRunning, corrida pedestre em natureza, com três provas, Trail Longo (TL) K25+, Trail Curto (TC) K12+ e Caminhada. Com partida e chegada junto do Estabelecimento Prisional de Sintra, Quinta do Bom Despacho, concelho de Sintra, distrito de Lisboa, visa a promoção e divulgação turística e ambiental da região, e da promoção do desporto em meio natural.</p>\n\n\n",
  "description_short": "Trail panorâmico pelos arredores de Sintra com partida junto ao Estabelecimento Prisional",
  "page": "https://www.trilhoperdido.com/evento/Trail-do-Bom-Despacho",
  "slug": "trail-do-bom-despacho-2024",
  "administrative_area_level_1": "Lisboa",
  "administrative_area_level_2": "Sintra",
  "administrative_area_level_3": "União das freguesias de Sintra (Santa Maria e São Miguel, São Martinho e São Pedro de Penaferrim)",
  "district_code": 11
}
