{
  "id": 34768,
  "name": "Corrida 4 Estações, Venda da Luísa 2024",
  "location": "Venda da Luísa, Condeixa",
  "coordinates": {
    "lat": 40.1141535,
    "lon": -8.498116399999999
  },
  "country": "Portugal",
  "locality": "Coimbra",
  "distances": [
    10000
  ],
  "types": [
    "10k",
    "run"
  ],
  "images": [
    "media/3410810a7f744f1bde02b909df0209b9"
  ],
  "start_date": "2024-04-07",
  "end_date": "2024-04-08",
  "circuit": [],
  "description": "\n<p>A Associação Desportiva 4 Estações com o apoio da Câmara Municipal de Condeixa a, vai realizar no dia 7 de Abril de 2024 pelas 10.30h na vila da Venda da Luísa a corrida de atletismo de estrada com a distância de cerca de 10km num, designada por Corrida das 4 Estações Primavera Venda da Luísa. Esta prova faz parte do Circuito de Corrida 4 Estações Portugal.</p>\n",
  "description_short": "Corrida de primavera em Venda da Luísa integrada no Circuito 4 Estações com apoio municipal",
  "page": "https://corrida4estacoesportugal.wordpress.com/inscricoes-17/0A_KuwdTkZcbQwk",
  "slug": "corrida-4-estacoes-venda-da-luisa-2024",
  "administrative_area_level_1": "Coimbra",
  "administrative_area_level_2": "Condeixa-a-Nova",
  "administrative_area_level_3": "União das freguesias de Condeixa-a-Velha e Condeixa-a-Nova",
  "district_code": 6
}
