{
  "id": 35249,
  "name": "Corrida A.C.S. 2024",
  "location": "São Brás de Alportel, Faro",
  "coordinates": {
    "lat": 37.152576,
    "lon": -7.889052299999999
  },
  "country": "Portugal",
  "locality": "Faro",
  "distances": [
    5000,
    9000,
    10000
  ],
  "types": [
    "run",
    "10k",
    "kids",
    "walk"
  ],
  "images": [
    "media/c76d7b6e132bb81f6ac3e7ebe05ce32b"
  ],
  "start_date": "2024-06-08",
  "end_date": "2024-06-09",
  "circuit": [],
  "description": "\n<p>O percurso da corrida é totalmente de asfalto com uma distância total aproximada de 10km, para<br>Concluir a prova será necessário perfazer 2 voltas de cerca 5km cada.</p>\n\n\n\n<p>Para a caminhada, o percurso é misto (Asfalto, terra batida e trilhos) com 1 volta única de<br>aproximadamente 9km.</p>\n\n\n\n<p>A prova inicia-se no Pavilhão Municipal de São Brás de Alportel, percorrendo as principais artérias da<br>vila e circulares, terminando novamente no Pavilhão Municipal.</p>\n\n\n\n<p></p>\n\n\n",
  "description_short": "Corrida urbana de 10km em dois circuitos pela vila de São Brás de Alportel",
  "page": "https://www.crono.aaalgarve.org/eventos/11-corrida-acs",
  "slug": "corrida-a-c-s-2024",
  "administrative_area_level_1": "Faro",
  "administrative_area_level_2": "São Brás de Alportel",
  "administrative_area_level_3": "São Brás de Alportel",
  "district_code": 8
}
