{
  "id": 36151,
  "name": "Urban Obstacles Sobral de Monte Agraço 2024",
  "location": "Sobral de Monte Agraço, Lisboa",
  "coordinates": {
    "lat": 39.0188114,
    "lon": -9.1505771
  },
  "country": "Portugal",
  "locality": "Lisboa",
  "distances": [],
  "types": [
    "trail",
    "run"
  ],
  "images": [
    "media/55dacd53e6e982a9d4256b43a592ee30"
  ],
  "start_date": "2024-10-27",
  "end_date": "2024-10-28",
  "circuit": [],
  "description": "\n<p>A Urban Obstacles regressa em Outubro ao Sobral de Monte Agraço para mais uma edição, num um percurso desafiante que terá três distâncias para colocares as tuas capacidades à prova. A cerca de 30 minutos de Lisboa a prova terá partida e chegada no Crossódromo Casais de Santo Quintino.</p>\n",
  "description_short": "Prova de obstáculos em Sobral de Monte Agraço com circuito desafiante a curta distância de Lisboa",
  "page": "https://lap2go.com/pt/event/urban-obstacles-sobral-mte-agraco-2024",
  "slug": "urban-obstacles-sobral-de-monte-agraco-2024",
  "administrative_area_level_1": "Lisboa",
  "administrative_area_level_2": "Sobral de Monte Agraço",
  "administrative_area_level_3": "Sobral de Monte Agraço",
  "district_code": 11
}
