{
  "id": 36284,
  "name": "Trail A-do-Barbas 2024",
  "location": "Maceira, Leiria",
  "coordinates": {
    "lat": 39.685696,
    "lon": -8.8841275
  },
  "country": "Portugal",
  "locality": "Leiria",
  "distances": [
    13000,
    21000
  ],
  "types": [
    "run",
    "trail",
    "cross-country"
  ],
  "images": [
    "media/95cf77e992c2d8c5eac45f1f39b40c58"
  ],
  "start_date": "2024-10-06",
  "end_date": "2024-10-07",
  "circuit": [],
  "description": "\n<p>O Centro Popular e Recreativo de A-do-Barbas em co-organização da ADAL, com o apoio da Câmara Municipal de Leiria, Junta de Freguesia de Maceira e junta da União de Freguesias de Pataias e Martingança, organiza no dia&nbsp;<strong>6 de outubro de 2024&nbsp;</strong>a<strong>&nbsp;8ª Edição do Cross/Trail CPR. A-do-Barbas</strong>, que consiste numa prova de Trail, na localidade de A-do-Barbas com partida e chegada junto à sede do Centro Popular e Recreativo de A-do-Barbas.</p>\n\n\n\n<p>A prova é constituída no seu percurso por trilhos, carreiros e caminhos com pouco desnível, o&nbsp;percurso alia beleza e técnica conciliada com alguma dureza.&nbsp;</p>\n\n\n\n<p>O evento é composto por&nbsp;<strong><u>duas provas competitivas</u></strong>:</p>\n\n\n\n<p><strong>T21 Km</strong>&nbsp;&#8211; Percurso com cerca de +/-21km de fácil progressão, mas com pouco desnível positivo.</p>\n\n\n\n<p><strong>T13 Km</strong>&nbsp;&#8211; Percurso com cerca de +/-13km de fácil progressão, mas com pouco desnível positivo, ideal para iniciantes à prática de Trail Running.</p>\n",
  "description_short": "Trail técnico e desafiante em A-do-Barbas com dois percursos de diferentes distâncias",
  "page": "https://www.recordepessoal.pt/evento/cross-trailcpra-do-barbas-8edicao",
  "slug": "trail-a-do-barbas-2024",
  "administrative_area_level_1": "Leiria",
  "administrative_area_level_2": "Leiria",
  "administrative_area_level_3": "Maceira",
  "district_code": 10
}
