{
  "id": 36731,
  "name": "Trail do Viso 2024",
  "location": "Guisande, Santa Maria da Feira",
  "coordinates": {
    "lat": 40.9695961,
    "lon": -8.4787202
  },
  "country": "Portugal",
  "locality": "Aveiro",
  "distances": [],
  "types": [
    "trail",
    "walk"
  ],
  "images": [
    "media/211337ae38b34a80410894f500a838b0"
  ],
  "start_date": "2024-10-27",
  "end_date": "2024-10-28",
  "circuit": [],
  "description": "\n<p>O Trail do Viso é um evento desportivo com duas vertentes, um Trail com cariz competitivo e uma Caminhada com cariz recreativo que permitirá aos participantes partir da Capela do Viso de Guisande e percorrer trilhos de beleza extrema do concelho de Santa Maria da Feira.</p>\n\n\n",
  "description_short": "Trail desafiante por trilhos históricos no concelho de Santa Maria da Feira, com partida da Capela do Viso de Guisande",
  "page": "https://lap2go.com/pt/event/trail-do-viso-2024",
  "slug": "trail-do-viso-2024",
  "administrative_area_level_1": "Aveiro",
  "administrative_area_level_2": "Santa Maria da Feira",
  "administrative_area_level_3": "Guisande",
  "district_code": 1
}
