{
  "id": 36970,
  "name": "Grande Prémio Natal 2024",
  "location": "Benfica, Lisboa",
  "coordinates": {
    "lat": 38.7510519,
    "lon": -9.2026693
  },
  "country": "Portugal",
  "locality": "Lisboa",
  "distances": [
    4000,
    10000
  ],
  "types": [
    "run",
    "10k",
    "kids",
    "walk"
  ],
  "images": [
    "media/f4781632d31fe8fde6931f45254f5210"
  ],
  "start_date": "2024-12-08",
  "end_date": "2024-12-09",
  "circuit": [],
  "description": "\n<p>O Continental Grande Prémio de Natal é organizado pela Associação de Atletismo de Lisboa e pela Last Lap Eventos Lda.<br>No dia 8 de dezembro de 2024 irá realizar-se o 65º Continental Grande Prémio de Natal, que se caracteriza por ser realizado na quadra natalícia, pelo percurso fácil que atravessa as principais artérias da cidade de Lisboa.<br>É um evento de corrida de estrada, com a distância de 10.000 metros, uma caminhada de cerca de 4.000 metros e outras corridas juvenis com distâncias ajustadas a cada idade</p>\n\n\n\n<p><br></p>\n",
  "description_short": "Corrida de Natal pelas principais artérias de Lisboa com percurso tradicional e ambiente festivo",
  "page": "https://lap2go.com/pt/event/grande-premio-de-natal-lisboa-2024",
  "slug": "grande-premio-natal-2024",
  "administrative_area_level_1": "Lisboa",
  "administrative_area_level_2": "Lisboa",
  "administrative_area_level_3": "Benfica",
  "district_code": 11
}
