{
  "id": 38660,
  "name": "Ultra Caminhos do Tejo 2025",
  "location": "Ourém, Santarém",
  "coordinates": {
    "lat": 39.6564974,
    "lon": -8.5773408
  },
  "country": "Portugal",
  "locality": "Santarém",
  "distances": [
    42195,
    57000,
    144000
  ],
  "types": [
    "trail",
    "marathon",
    "run"
  ],
  "images": [
    "media/0305c9672ae777f328f1ea160d90bddc"
  ],
  "start_date": "2025-06-06",
  "end_date": "2025-06-07",
  "circuit": [
    "ATRP"
  ],
  "description": "\n<p>A Associação Desportiva O Mundo da Corrida.com, com o Apoio da Câmara Municipal de Ourém, realiza nos dias 6 e 7 de Junho de 2025 uma corrida denominada&nbsp;&nbsp;<strong>&#8220;XVIII Ultra Maratona Caminhos do Tejo&#8221;</strong>&nbsp;,&nbsp;com&nbsp;&nbsp;uma distância de 144 km.<br>Realiza-se&nbsp;uma corrida mais curta de 57 km com partida de Santarém.</p>\n\n\n\n<p>A partida da &#8220;XVIII Ultra Maratona Caminhos do Tejo&#8221;&nbsp;será dada às 20:00 horas do dia 6 de Junho de 2025, no km 0 ao lado do Pavilhão de Portugal, no Parque das Nações, seguindo os caminhos de peregrinação até ao Santuário de Fátima.&nbsp;</p>\n\n\n\n<p>A partida da prova de 57 km a partir de Santarém será dada às 9 horas da manhã do dia 7 de Junho de 2025, na antiga Escola Prática de Cavalaria, seguindo o mesmo percurso da prova que parte de Lisboa.</p>\n\n\n\n<p></p>\n\n\n",
  "description_short": "Ultra maratona histórica pelos caminhos do Tejo, ligando Lisboa a Fátima e envolvendo Santarém",
  "page": "https://www.omdceventos.com/evento/xviii-ultra-caminhos-do-tejo",
  "slug": "ultra-caminhos-do-tejo-2025",
  "administrative_area_level_1": "Santarém",
  "administrative_area_level_2": "Ourém",
  "administrative_area_level_3": "Olival",
  "district_code": 14
}
