{
  "id": 39123,
  "name": "Trail Anadia Capital do Espumante 2025",
  "location": "Anadia, Aveiro",
  "coordinates": {
    "lat": 40.4409572,
    "lon": -8.4354306
  },
  "country": "Portugal",
  "locality": "Aveiro",
  "distances": [],
  "types": [
    "trail"
  ],
  "images": [
    "media/17e647486c5e4839609895ac9b25e30c"
  ],
  "start_date": "2025-05-25",
  "end_date": "2025-05-26",
  "circuit": [
    "ATRP"
  ],
  "description": "\n<p>O Trail Anadia capital do espumante, prova certificada pelo ATRP – Associação de Trail Running de Portugal, que faz parte do circuito nacional de trail, circuito nacional de sprint e circuito jovem, do ano 2024/2025 da ATRP, sob a égide da FPA – Federação Portuguesa de Atletismo, vai-se realizar na cidade de Anadia, no dia 25/05/2025, distrito de Aveiro e é organizado pelo Clube Saca Trilhos Anadia, com o apoio da Câmara Municipal de Anadia, da União de freguesias de Arcos e de Mogofores, da junta de freguesia da Moita, da junta de freguesia de Avelãs de Cima. Tem como principais “sponsors” as Caves da Montanha, a Nova Casa dos Leitões e o ginásio Cross Company.<br>A prova de distância de trail longo Caves da Montanha e trail Curto Nova Casa dos Leitões contam ainda para o circuito distrital de trail da Associação de Atletismo de Aveiro, das respetivas distâncias. A prova de distância de trail longo Caves da Montanha, atribui os títulos de campeões distritais de trail da Associação de Atletismo de Aveiro.</p>\n",
  "description_short": "Trail desafiante por Anadia com provas de trail running certificadas e apoiadas pela autarquia",
  "page": "https://stopandgo.net/events/trail-anadia-capital-do-espumante-2025",
  "slug": "trail-anadia-capital-do-espumante-2025",
  "administrative_area_level_1": "Aveiro",
  "administrative_area_level_2": "Anadia",
  "administrative_area_level_3": null,
  "district_code": 1
}
