{
  "id": 41050,
  "name": "Meia Maratona Terra Única 2025",
  "location": "Vila Nova de Santo André, Santiago do Cacém",
  "coordinates": {
    "lat": 38.0588998,
    "lon": -8.7844006
  },
  "country": "Portugal",
  "locality": "Setúbal",
  "distances": [
    21097
  ],
  "types": [
    "run",
    "half-marathon"
  ],
  "images": [
    "media/4eca4c4bb58de77ecdc5f9fd3258436d"
  ],
  "start_date": "2025-05-04",
  "end_date": "2025-05-04",
  "circuit": [],
  "description": "\n<p>A Câmara Municipal de Santiago do Cacém, com o apoio da Junta Freguesia de Santo André e de associações desportivas do Município, organiza a 1.ª edição da Meia Maratona Terra Única, a realizar em Vila Nova de Santo André.</p>\n\n\n\n<p></p>\n",
  "description_short": "Meia maratona inaugural em Vila Nova de Santo André com organização municipal",
  "page": "https://acorrer.pt/eventos/3848/info",
  "slug": "meia-maratona-terra-unica-2025",
  "administrative_area_level_1": "Setúbal",
  "administrative_area_level_2": "Santiago do Cacém",
  "administrative_area_level_3": "Santo André",
  "district_code": 15
}
