{
  "id": 41250,
  "name": "Corrida da Liberdade 2025",
  "location": "Vila Nova da Barquinha, Santarém",
  "coordinates": {
    "lat": 39.2366618,
    "lon": -8.686011900000002
  },
  "country": "Portugal",
  "locality": "Santarém",
  "distances": [
    10000
  ],
  "types": [
    "run",
    "10k",
    "kids"
  ],
  "images": [
    "media/f31d74ad6ae7209de99ca804bf3d592c"
  ],
  "start_date": "2025-04-25",
  "end_date": "2025-04-25",
  "circuit": [],
  "description": "\n<p>A organização do evento é da responsabilidade do Município de Vila Nova da Barquinha, tendo<br>como principal objetivo a comemoração do dia 25 de Abril através de atividades desportivas e<br>recreativas.</p>\n\n\n\n<p></p>\n",
  "description_short": "Corrida comemorativa do 25 de Abril organizada pela câmara municipal de Vila Nova da Barquanha",
  "page": "https://www.trilhoperdido.com/evento/Corrida-da-Liberdade",
  "slug": "corrida-da-liberdade-2025",
  "administrative_area_level_1": "Santarém",
  "administrative_area_level_2": "Santarém",
  "administrative_area_level_3": "União de freguesias da cidade de Santarém",
  "district_code": 14
}
